queue_agnostic/__init__.py
queue_agnostic/queue_factory.py
queue_agnostic/queue_interface.py
queue_agnostic/adapters/__init__.py
queue_agnostic/adapters/aws_sqs_adapter.py
queue_agnostic/adapters/azure_servicebus_adapter.py
queue_agnostic/adapters/gcp_pubsub_adapter.py
queue_agnostic/adapters/rabbitmq_adapter.py
queue_agnostic-1.0.0.dist-info/licenses/LICENSE
queue_agnostic-1.0.0.dist-info/METADATA
queue_agnostic-1.0.0.dist-info/WHEEL
queue_agnostic-1.0.0.dist-info/top_level.txt
queue_agnostic-1.0.0.dist-info/RECORD
