Metadata-Version: 2.4
Name: queue-agnostic
Version: 1.0.0
Summary: Universal queue abstraction library supporting RabbitMQ, AWS SQS, Azure Service Bus, and GCP Pub/Sub
Home-page: https://github.com/onezippy/queue-agnostic-python
Author: OneZippy
Author-email: 
Classifier: Development Status :: 4 - Beta
Classifier: Intended Audience :: Developers
Classifier: Topic :: Software Development :: Libraries :: Python Modules
Classifier: License :: OSI Approved :: MIT License
Classifier: Programming Language :: Python :: 3
Classifier: Programming Language :: Python :: 3.8
Classifier: Programming Language :: Python :: 3.9
Classifier: Programming Language :: Python :: 3.10
Classifier: Programming Language :: Python :: 3.11
Requires-Python: >=3.8
License-File: LICENSE
Requires-Dist: aio-pika>=9.0.0
Requires-Dist: aioboto3>=11.0.0
Requires-Dist: azure-servicebus>=7.11.0
Requires-Dist: google-cloud-pubsub>=2.18.0
Provides-Extra: dev
Requires-Dist: pytest>=7.0.0; extra == "dev"
Requires-Dist: pytest-asyncio>=0.21.0; extra == "dev"
Requires-Dist: python-dotenv>=1.0.0; extra == "dev"
Dynamic: author
Dynamic: classifier
Dynamic: description
Dynamic: description-content-type
Dynamic: home-page
Dynamic: license-file
Dynamic: provides-extra
Dynamic: requires-dist
Dynamic: requires-python
Dynamic: summary
